agentic/__init__.py
agentic/actor_agents.py
agentic/agentic_secrets.py
agentic/api.py
agentic/cli.py
agentic/colors.py
agentic/common.py
agentic/context_manager.py
agentic/event_factory.py
agentic/events.py
agentic/file_cache.py
agentic/fix_console.py
agentic/llm.py
agentic/model_mock.py
agentic/models.py
agentic/quiet_warnings.py
agentic/ray_mock.py
agentic/runner.py
agentic/settings.py
agentic/thread_manager.py
agentic/workflow.py
agentic/custom_models/mock_provider.py
agentic/dashboard/README.md
agentic/dashboard/__init__.py
agentic/dashboard/components.json
agentic/dashboard/next-env.d.ts
agentic/dashboard/next.config.js
agentic/dashboard/package.json
agentic/dashboard/postcss.config.js
agentic/dashboard/setup.py
agentic/dashboard/tailwind.config.ts
agentic/dashboard/tsconfig.json
agentic/dashboard/types.d.ts
agentic/dashboard/src/app/favicon.ico
agentic/dashboard/src/app/globals.css
agentic/dashboard/src/app/layout.tsx
agentic/dashboard/src/app/page.tsx
agentic/dashboard/src/app/api/[...path]/route.ts
agentic/dashboard/src/app/components/AgentChat.tsx
agentic/dashboard/src/app/components/AgentSidebar.tsx
agentic/dashboard/src/app/components/BackgroundTasks.tsx
agentic/dashboard/src/app/components/ChatInputForm.tsx
agentic/dashboard/src/app/components/EventLogs.tsx
agentic/dashboard/src/app/components/MarkdownRenderer.tsx
agentic/dashboard/src/app/components/ReasoningDisplay.tsx
agentic/dashboard/src/app/components/ThreadsTable.tsx
agentic/dashboard/src/app/components/ui/accordion.tsx
agentic/dashboard/src/app/components/ui/alert.tsx
agentic/dashboard/src/app/components/ui/auto-scroll-area.tsx
agentic/dashboard/src/app/components/ui/avatar.tsx
agentic/dashboard/src/app/components/ui/button.tsx
agentic/dashboard/src/app/components/ui/card.tsx
agentic/dashboard/src/app/components/ui/dropdown-menu.tsx
agentic/dashboard/src/app/components/ui/input.tsx
agentic/dashboard/src/app/components/ui/label.tsx
agentic/dashboard/src/app/components/ui/scroll-area.tsx
agentic_framework-0.3.11.dist-info/licenses/LICENSE
agentic_framework-0.3.11.dist-info/METADATA
agentic_framework-0.3.11.dist-info/WHEEL
agentic_framework-0.3.11.dist-info/entry_points.txt
agentic_framework-0.3.11.dist-info/top_level.txt
agentic_framework-0.3.11.dist-info/RECORD
