Metadata-Version: 2.4
Name: agentic-framework
Version: 0.3.11
Summary: An opinionated framework for building sophisticated AI Agents
Requires-Python: <3.13,>=3.11
License-File: LICENSE
Requires-Dist: aiofiles==24.1.0
Requires-Dist: cryptography==44.0.3
Requires-Dist: fastapi==0.115.12
Requires-Dist: html2text==2025.4.15
Requires-Dist: httpx==0.28.1
Requires-Dist: jinja2==3.1.6
Requires-Dist: openai==1.104.1
Requires-Dist: numpy==2.2.5
Requires-Dist: pandas==2.2.3
Requires-Dist: pydantic==2.11.4
Requires-Dist: pypdf2==3.0.1
Requires-Dist: python-magic==0.4.27
Requires-Dist: pyyaml==6.0.2
Requires-Dist: ray[serve]==2.45.0
Requires-Dist: requests==2.32.3
Requires-Dist: sqlmodel==0.0.24
Requires-Dist: sse-starlette==2.3.4
Requires-Dist: textract-supercog==1.6.5.post1
Requires-Dist: thespian==4.0.1
Requires-Dist: typer==0.15.4
Requires-Dist: click==8.1.8
Requires-Dist: litellm>=1.72.1
Provides-Extra: streamlit
Requires-Dist: streamlit==1.45.0; extra == "streamlit"
Provides-Extra: rag
Requires-Dist: weaviate-client==4.14.1; extra == "rag"
Requires-Dist: chonkie[semantic]==1.0.6; extra == "rag"
Requires-Dist: transformers==4.51.3; extra == "rag"
Requires-Dist: torch==2.6.0; platform_system == "Darwin" and extra == "rag"
Requires-Dist: torch==2.6.0; (platform_system == "Linux" or platform_system == "Windows") and extra == "rag"
Requires-Dist: grpcio==1.71.0; extra == "rag"
Requires-Dist: fastembed==0.6.1; extra == "rag"
Requires-Dist: extract-msg==0.29.0; extra == "rag"
Provides-Extra: airbnb
Requires-Dist: icalendar==6.1.3; extra == "airbnb"
Provides-Extra: browser-use
Requires-Dist: browser-use==0.1.40; extra == "browser-use"
Requires-Dist: playwright==1.52.0; extra == "browser-use"
Requires-Dist: langchain==0.3.25; extra == "browser-use"
Requires-Dist: langchain-google-genai==2.1.4; extra == "browser-use"
Requires-Dist: langchain-community==0.3.19; extra == "browser-use"
Provides-Extra: database
Requires-Dist: psycopg2-binary==2.9.10; extra == "database"
Requires-Dist: sqlalchemy==2.0.40; extra == "database"
Provides-Extra: duckduckgo
Requires-Dist: duckduckgo-search==8.0.1; extra == "duckduckgo"
Provides-Extra: geolocation
Requires-Dist: tzlocal==5.3.1; extra == "geolocation"
Provides-Extra: github
Requires-Dist: gitpython==3.1.44; extra == "github"
Provides-Extra: google-news
Requires-Dist: google-news-feed==1.1.0; extra == "google-news"
Requires-Dist: googlenewsdecoder==0.1.7; extra == "google-news"
Provides-Extra: image-generator
Requires-Dist: boto3==1.38.9; extra == "image-generator"
Provides-Extra: imap
Requires-Dist: beautifulsoup4==4.13.4; extra == "imap"
Provides-Extra: mcp
Requires-Dist: mcp[cli]==1.7.1; extra == "mcp"
Provides-Extra: meeting-baas
Requires-Dist: agentic-framework[rag]; extra == "meeting-baas"
Requires-Dist: sqlalchemy==2.0.40; extra == "meeting-baas"
Provides-Extra: playwright
Requires-Dist: playwright==1.52.0; extra == "playwright"
Provides-Extra: podcast
Requires-Dist: beautifulsoup4==4.13.4; extra == "podcast"
Provides-Extra: text-to-speech
Requires-Dist: pydub==0.25.1; extra == "text-to-speech"
Provides-Extra: all-tools
Requires-Dist: agentic-framework[airbnb,browser-use,database,duckduckgo,geolocation,github,google-news,image-generator,imap,mcp,meeting-baas,playwright,text-to-speech]; extra == "all-tools"
Provides-Extra: all
Requires-Dist: agentic-framework[all-tools,rag,streamlit]; extra == "all"
Provides-Extra: dev
Requires-Dist: pytest==8.3.5; extra == "dev"
Requires-Dist: pytest-asyncio==0.26.0; extra == "dev"
Requires-Dist: debugpy==1.8.14; extra == "dev"
Requires-Dist: black==25.1.0; extra == "dev"
Requires-Dist: mkdocs-material==9.6.12; extra == "dev"
Requires-Dist: mkdocs-swagger-ui-tag==0.7.1; extra == "dev"
Requires-Dist: mike==2.1.3; extra == "dev"
Requires-Dist: pytest-mock; extra == "dev"
Dynamic: license-file
